alliance_platform/py.typed
alliance_platform/server_choices/__init__.py
alliance_platform/server_choices/apps.py
alliance_platform/server_choices/class_handlers/django_filters.py
alliance_platform/server_choices/class_handlers/form.py
alliance_platform/server_choices/class_handlers/registry.py
alliance_platform/server_choices/class_handlers/rest_framework.py
alliance_platform/server_choices/decorators.py
alliance_platform/server_choices/field_registry.py
alliance_platform/server_choices/pagination.py
alliance_platform/server_choices/settings.py
alliance_platform/server_choices/templates/alliance_platform/server_choices/widgets/server_choices_select_widget.html
alliance_platform/server_choices/views.py
alliance_platform_server_choices-0.0.2.dist-info/METADATA
alliance_platform_server_choices-0.0.2.dist-info/WHEEL
alliance_platform_server_choices-0.0.2.dist-info/entry_points.txt
alliance_platform_server_choices-0.0.2.dist-info/RECORD
